postgis/pg.py
postgis/pgis.py
postgis/ps.py
postgis_assist-0.0.3.dist-info/LICENSE
postgis_assist-0.0.3.dist-info/METADATA
postgis_assist-0.0.3.dist-info/WHEEL
postgis_assist-0.0.3.dist-info/top_level.txt
postgis_assist-0.0.3.dist-info/RECORD
