Metadata-Version: 2.1
Name: postgis-assist
Version: 0.0.3
Summary: Package for Postgis query using python
Home-page: https://github.com/kaditya97/postgis-assist
Author: Aditya Kushwaha
Author-email: kaditya9711@gmail.com
License: UNKNOWN
Keywords: postgresql,postgres,database,sql,api,table,pg,postGIS
Platform: UNKNOWN
Classifier: Programming Language :: Python :: 3
Classifier: License :: OSI Approved :: MIT License
Classifier: Operating System :: OS Independent
Requires-Python: >=3.6
Requires-Dist: psycopg2
